README.md
setup.py
Raindeer/__init__.py
Raindeer/ext.py
Raindeer.egg-info/PKG-INFO
Raindeer.egg-info/SOURCES.txt
Raindeer.egg-info/dependency_links.txt
Raindeer.egg-info/requires.txt
Raindeer.egg-info/top_level.txt
Raindeer/config/__init__.py